esdbcat/__init__.py
esdbcat/cli.py
esdbcat-0.2.0.dist-info/METADATA
esdbcat-0.2.0.dist-info/WHEEL
esdbcat-0.2.0.dist-info/entry_points.txt
esdbcat-0.2.0.dist-info/licenses/LICENSE
esdbcat-0.2.0.dist-info/RECORD
