Metadata-Version: 2.3
Name: esdbcat
Version: 0.2.0
Summary: EventStore CLI tool for reading and following streams
Project-URL: Homepage, https://github.com/funkwerk-mobility/esdbcat
Project-URL: Documentation, https://github.com/funkwerk-mobility/esdbcat#readme
Project-URL: Repository, https://github.com/funkwerk-mobility/esdbcat.git
Author-email: Mathis Beer <mathis_beer@funkwerk.com>
License: BSL-1.0
Keywords: cli,events,eventstore,streaming
Classifier: Development Status :: 4 - Beta
Classifier: Environment :: Console
Classifier: Intended Audience :: Developers
Classifier: License :: OSI Approved :: Boost Software License 1.0 (BSL-1.0)
Classifier: Programming Language :: Python :: 3
Classifier: Programming Language :: Python :: 3.8
Classifier: Programming Language :: Python :: 3.9
Classifier: Programming Language :: Python :: 3.10
Classifier: Programming Language :: Python :: 3.11
Classifier: Topic :: Database
Classifier: Topic :: Software Development :: Libraries :: Python Modules
Classifier: Topic :: Utilities
Requires-Python: >=3.8
Requires-Dist: click>=8.0.0
Requires-Dist: esdbclient>=0.4.0
Requires-Dist: protobuf>=5.0.0
Provides-Extra: test
Requires-Dist: pytest>=7.0.0; extra == 'test'
Requires-Dist: testcontainers>=3.7.0; extra == 'test'
Provides-Extra: validate
Requires-Dist: build>=1.0.0; extra == 'validate'
Requires-Dist: check-wheel-contents>=0.4.0; extra == 'validate'
Requires-Dist: mypy>=1.9.0; extra == 'validate'
Requires-Dist: ruff>=0.3.0; extra == 'validate'
Requires-Dist: twine>=4.0.0; extra == 'validate'
